torchensemble/__init__.py
torchensemble/_base.py
torchensemble/_constants.py
torchensemble/adversarial_training.py
torchensemble/bagging.py
torchensemble/fast_geometric.py
torchensemble/fusion.py
torchensemble/gradient_boosting.py
torchensemble/snapshot_ensemble.py
torchensemble/soft_gradient_boosting.py
torchensemble/voting.py
torchensemble/utils/__init__.py
torchensemble/utils/dataloder.py
torchensemble/utils/io.py
torchensemble/utils/logging.py
torchensemble/utils/operator.py
torchensemble/utils/set_module.py
torchensemble-0.2.0.dist-info/LICENSE
torchensemble-0.2.0.dist-info/METADATA
torchensemble-0.2.0.dist-info/WHEEL
torchensemble-0.2.0.dist-info/top_level.txt
torchensemble-0.2.0.dist-info/RECORD
